setup.py
tornadwwo/__init__.py
tornadwwo/wwo.py
tornadwwo.egg-info/PKG-INFO
tornadwwo.egg-info/SOURCES.txt
tornadwwo.egg-info/dependency_links.txt
tornadwwo.egg-info/requires.txt
tornadwwo.egg-info/setup_requires.txt
tornadwwo.egg-info/top_level.txt