Metadata-Version: 1.0
Name: tornadwwo
Version: 0.1.2
Summary: Async API calls for World Weather Online
Home-page: https://github.com/abdelouahabb/tornadwwo
Author: ALIANE Abdenour Abdelouahab
Author-email: abdelouahab_al@yahoo.fr
License: MIT
Keywords: tornado weather non-blocking api http
Platform: UNKNOWN
